subman/__init__.py
subman/exceptions.py
subman/machine.py
subman/py.typed
subman/subman.py
subman-0.1.1.dist-info/LICENSE
subman-0.1.1.dist-info/METADATA
subman-0.1.1.dist-info/WHEEL
subman-0.1.1.dist-info/top_level.txt
subman-0.1.1.dist-info/RECORD
