Metadata-Version: 2.1
Name: subman
Version: 0.1.1
Summary: Powerful Python package to manage subscriptions.
Home-page: https://github.com/cde-ev/subman
Author: Lars Esser, Maarten Grothus, Tobias Udtke
Author-email: 
Maintainer: CdE-Datenbank development team
Maintainer-email: cdedb@lists.cde-ev.de
Project-URL: Bug Tracker, https://github.com/cde-ev/subman/issues
Keywords: subscription,mailinglist,opt-out
Classifier: Development Status :: 5 - Production/Stable
Classifier: Intended Audience :: Developers
Classifier: Programming Language :: Python :: 3
Classifier: License :: OSI Approved :: GNU General Public License v3 or later (GPLv3+)
Classifier: Operating System :: OS Independent
Classifier: Typing :: Typed
Requires-Python: >=3.8
License-File: LICENSE
